{"pokemon":{"id":10041,"identifier":"gyarados-mega","species_id":130,"height":65,"weight":3050,"base_experience":224,"order":174,"is_default":0},"species_name":{"pokemon_species_id":130,"local_language_id":9,"name":"Gyarados","genus":"Atrocious"},"species_flavor_text":{"species_id":130,"version_id":26,"language_id":9,"flavor_text":"Once Gyarados goes on a rampage, its ferociously violent\nblood doesn’t calm until it has burned everything down.\nThere are records of this Pokémon’s rampages lasting a\nwhole month."},"form":{"id":10141,"identifier":"gyarados-mega","form_identifier":"mega","pokemon_id":10041,"introduced_in_version_group_id":15,"is_default":1,"is_battle_only":1,"is_mega":1,"form_order":2,"order":175},"form_name":{"pokemon_form_id":10141,"local_language_id":9,"form_name":"Mega Gyarados","pokemon_name":"Mega Gyarados"}}