{"pokemon":{"id":114,"identifier":"tangela","species_id":114,"height":10,"weight":350,"base_experience":87,"order":145,"is_default":1},"species_name":{"pokemon_species_id":114,"local_language_id":9,"name":"Tangela","genus":"Vine"},"species_flavor_text":{"species_id":114,"version_id":26,"language_id":9,"flavor_text":"Tangela’s vines snap off easily if they are grabbed. This\nhappens without pain, allowing it to make a quick getaway.\nThe lost vines are replaced by newly grown vines the very\nnext day."},"form":{"id":114,"identifier":"tangela","form_identifier":"","pokemon_id":114,"introduced_in_version_group_id":1,"is_default":1,"is_battle_only":0,"is_mega":0,"form_order":1,"order":146}}