{"pokemon":{"id":176,"identifier":"togetic","species_id":176,"height":6,"weight":32,"base_experience":142,"order":227,"is_default":1},"species_name":{"pokemon_species_id":176,"local_language_id":9,"name":"Togetic","genus":"Happiness"},"species_flavor_text":{"species_id":176,"version_id":26,"language_id":9,"flavor_text":"Togetic is said to be a Pokémon that brings good fortune.\nWhen the Pokémon spots someone who is pure of heart,\nit is said to appear and share its happiness with that person."},"form":{"id":176,"identifier":"togetic","form_identifier":"","pokemon_id":176,"introduced_in_version_group_id":3,"is_default":1,"is_battle_only":0,"is_mega":0,"form_order":1,"order":228}}