{"pokemon":{"id":249,"identifier":"lugia","species_id":249,"height":52,"weight":2160,"base_experience":306,"order":301,"is_default":1},"species_name":{"pokemon_species_id":249,"local_language_id":9,"name":"Lugia","genus":"Diving"},"species_flavor_text":{"species_id":249,"version_id":26,"language_id":9,"flavor_text":"Lugia’s wings pack devastating power—a light fluttering of its\nwings can blow apart regular houses. As a result, this\nPokémon chooses to live out of sight deep under the sea."},"form":{"id":249,"identifier":"lugia","form_identifier":"","pokemon_id":249,"introduced_in_version_group_id":3,"is_default":1,"is_battle_only":0,"is_mega":0,"form_order":1,"order":328}}