{"pokemon":{"id":34,"identifier":"nidoking","species_id":34,"height":14,"weight":620,"base_experience":227,"order":47,"is_default":1},"species_name":{"pokemon_species_id":34,"local_language_id":9,"name":"Nidoking","genus":"Drill"},"species_flavor_text":{"species_id":34,"version_id":26,"language_id":9,"flavor_text":"Nidoking’s thick tail packs enormously destructive power.\nWith one swing, it can topple a metal transmission tower. Once\nthis Pokémon goes on a rampage, there is no stopping it."},"form":{"id":34,"identifier":"nidoking","form_identifier":"","pokemon_id":34,"introduced_in_version_group_id":1,"is_default":1,"is_battle_only":0,"is_mega":0,"form_order":1,"order":48}}