{"pokemon":{"id":349,"identifier":"feebas","species_id":349,"height":6,"weight":74,"base_experience":40,"order":417,"is_default":1},"species_name":{"pokemon_species_id":349,"local_language_id":9,"name":"Feebas","genus":"Fish"},"species_flavor_text":{"species_id":349,"version_id":26,"language_id":9,"flavor_text":"While Feebas’s body is in tatters, it has a hardy and tenacious\nlife force that enables it to live anywhere. However, this\nPokémon is also slow and dimwitted, making it an easy catch."},"form":{"id":349,"identifier":"feebas","form_identifier":"","pokemon_id":349,"introduced_in_version_group_id":5,"is_default":1,"is_battle_only":0,"is_mega":0,"form_order":1,"order":444}}