{"pokemon":{"id":40,"identifier":"wigglytuff","species_id":40,"height":10,"weight":120,"base_experience":196,"order":55,"is_default":1},"species_name":{"pokemon_species_id":40,"local_language_id":9,"name":"Wigglytuff","genus":"Balloon"},"species_flavor_text":{"species_id":40,"version_id":26,"language_id":9,"flavor_text":"Wigglytuff’s body is very flexible. By inhaling deeply,\nthis Pokémon can inflate itself seemingly without end.\nOnce inflated, Wigglytuff bounces along lightly like a balloon."},"form":{"id":40,"identifier":"wigglytuff","form_identifier":"","pokemon_id":40,"introduced_in_version_group_id":1,"is_default":1,"is_battle_only":0,"is_mega":0,"form_order":1,"order":56}}