{"pokemon":{"id":416,"identifier":"vespiquen","species_id":416,"height":12,"weight":385,"base_experience":166,"order":502,"is_default":1},"species_name":{"pokemon_species_id":416,"local_language_id":9,"name":"Vespiquen","genus":"Beehive"},"species_flavor_text":{"species_id":416,"version_id":26,"language_id":9,"flavor_text":"Its abdomen is a honeycomb for grubs. It raises its\ngrubs on honey collected by Combee."},"form":{"id":416,"identifier":"vespiquen","form_identifier":"","pokemon_id":416,"introduced_in_version_group_id":8,"is_default":1,"is_battle_only":0,"is_mega":0,"form_order":1,"order":531}}