{"pokemon":{"id":464,"identifier":"rhyperior","species_id":464,"height":24,"weight":2828,"base_experience":241,"order":141,"is_default":1},"species_name":{"pokemon_species_id":464,"local_language_id":9,"name":"Rhyperior","genus":"Drill"},"species_flavor_text":{"species_id":464,"version_id":26,"language_id":9,"flavor_text":"It puts rocks in holes in its palms and uses its\nmuscles to shoot them. Geodude are shot at\nrare times."},"form":{"id":464,"identifier":"rhyperior","form_identifier":"","pokemon_id":464,"introduced_in_version_group_id":8,"is_default":1,"is_battle_only":0,"is_mega":0,"form_order":1,"order":142}}