{"pokemon":{"id":48,"identifier":"venonat","species_id":48,"height":10,"weight":300,"base_experience":61,"order":65,"is_default":1},"species_name":{"pokemon_species_id":48,"local_language_id":9,"name":"Venonat","genus":"Insect"},"species_flavor_text":{"species_id":48,"version_id":26,"language_id":9,"flavor_text":"Venonat is said to have evolved with a coat of thin, stiff hair\nthat covers its entire body for protection. It possesses large\neyes that never fail to spot even minuscule prey."},"form":{"id":48,"identifier":"venonat","form_identifier":"","pokemon_id":48,"introduced_in_version_group_id":1,"is_default":1,"is_battle_only":0,"is_mega":0,"form_order":1,"order":66}}