{"pokemon":{"id":505,"identifier":"watchog","species_id":505,"height":11,"weight":270,"base_experience":147,"order":575,"is_default":1},"species_name":{"pokemon_species_id":505,"local_language_id":9,"name":"Watchog","genus":"Lookout"},"species_flavor_text":{"species_id":505,"version_id":26,"language_id":9,"flavor_text":"When they see an enemy, their tails stand high,\nand they spit the seeds of berries stored in their\ncheek pouches."},"form":{"id":505,"identifier":"watchog","form_identifier":"","pokemon_id":505,"introduced_in_version_group_id":11,"is_default":1,"is_battle_only":0,"is_mega":0,"form_order":1,"order":609}}