{"pokemon":{"id":643,"identifier":"reshiram","species_id":643,"height":32,"weight":3300,"base_experience":306,"order":718,"is_default":1},"species_name":{"pokemon_species_id":643,"local_language_id":9,"name":"Reshiram","genus":"Vast White"},"species_flavor_text":{"species_id":643,"version_id":26,"language_id":9,"flavor_text":"When Reshiram’s tail flares, the heat energy moves\nthe atmosphere and changes the world’s weather."},"form":{"id":643,"identifier":"reshiram","form_identifier":"","pokemon_id":643,"introduced_in_version_group_id":11,"is_default":1,"is_battle_only":0,"is_mega":0,"form_order":1,"order":758}}