{"pokemon":{"id":80,"identifier":"slowbro","species_id":80,"height":16,"weight":785,"base_experience":172,"order":99,"is_default":1},"species_name":{"pokemon_species_id":80,"local_language_id":9,"name":"Slowbro","genus":"Hermit Crab"},"species_flavor_text":{"species_id":80,"version_id":26,"language_id":9,"flavor_text":"Slowbro’s tail has a Shellder firmly attached with a bite.\nAs a result, the tail can’t be used for fishing anymore. This\ncauses Slowbro to grudgingly swim and catch prey instead."},"form":{"id":80,"identifier":"slowbro","form_identifier":"","pokemon_id":80,"introduced_in_version_group_id":1,"is_default":1,"is_battle_only":0,"is_mega":0,"form_order":1,"order":100}}